{
  "kind": "singleType",
  "collectionName": "homes",
  "info": {
    "singularName": "home",
    "pluralName": "homes",
    "displayName": "Home",
    "description": ""
  },
  "options": {
    "draftAndPublish": false
  },
  "pluginOptions": {},
  "attributes": {
    "greeting": {
      "type": "string",
      "required": true
    },
    "name": {
      "type": "string",
      "required": true
    },
    "title": {
      "type": "string",
      "required": true
    },
    "description": {
      "type": "text",
      "required": true
    }
  }
}
